airsim_adaptor/__init__.py
airsim_adaptor/client.py
airsim_adaptor/pfm.py
airsim_adaptor/types.py
airsim_adaptor/utils.py
airsim_adaptor-1.0.2.dist-info/LICENSE
airsim_adaptor-1.0.2.dist-info/METADATA
airsim_adaptor-1.0.2.dist-info/WHEEL
airsim_adaptor-1.0.2.dist-info/top_level.txt
airsim_adaptor-1.0.2.dist-info/RECORD
