Metadata-Version: 2.1
Name: airsim-adaptor
Version: 1.0.2
Summary: A customized airsim API adaptor for special purposes
Home-page: https://github.com/ibrahim0v
Author: ibrahim aydin
Author-email: noemail@sorry.com
License: UNKNOWN
Platform: UNKNOWN
Classifier: Programming Language :: Python :: 3
Classifier: License :: OSI Approved :: MIT License
Classifier: Operating System :: OS Independent
Requires-Python: >=3.6
